pm_ansible/__init__.py
pm_ansible/__main__.py
pm_ansible/cli/__init__.py
pm_ansible/cli/base.py
pm_ansible/cli/config.py
pm_ansible/cli/execute.py
pm_ansible/cli/inventory_parser.py
pm_ansible/cli/modules.py
pm_ansible/cli/reference.py
polemarch_ansible-3.0.1.dist-info/LICENSE
polemarch_ansible-3.0.1.dist-info/METADATA
polemarch_ansible-3.0.1.dist-info/WHEEL
polemarch_ansible-3.0.1.dist-info/entry_points.txt
polemarch_ansible-3.0.1.dist-info/top_level.txt
polemarch_ansible-3.0.1.dist-info/RECORD
