Metadata-Version: 2.1
Name: polemarch-ansible
Version: 3.0.1
Summary: Wrapper for Ansible cli.
Author-email: VST Consulting <sergey.k@vstconsulting.net>
License: GPLv3
Project-URL: Home, https://gitlab.com/vstconsulting/polemarch-ansible
Project-URL: Web Site, https://polemarch.org/
Project-URL: Issue Tracker, https://gitlab.com/vstconsulting/polemarch-ansible/issues
Project-URL: Source Code, https://gitlab.com/vstconsulting/polemarch-ansible
Project-URL: Documentation, https://about.polemarch.org/
Classifier: Development Status :: 5 - Production/Stable
Classifier: Operating System :: POSIX
Classifier: Programming Language :: Python
Classifier: Programming Language :: Python :: 3
Classifier: Programming Language :: Python :: 3 :: Only
Classifier: Programming Language :: Python :: 3.8
Classifier: Programming Language :: Python :: 3.9
Classifier: Programming Language :: Python :: 3.10
Classifier: Programming Language :: Python :: 3.11
Classifier: Programming Language :: Python :: 3.12
Classifier: License :: OSI Approved :: GNU General Public License v3 or later (GPLv3+)
Classifier: Programming Language :: Python :: Implementation :: CPython
Classifier: Topic :: System :: Systems Administration
Classifier: Topic :: Utilities
Requires-Python: >=3.8
License-File: LICENSE
Requires-Dist: ansible-core <2.19,>=2.11
